yafowil.widget.chosen-1.4-py3.9-nspkg.pth
yafowil/widget/chosen/__init__.py
yafowil/widget/chosen/example.py
yafowil/widget/chosen/tests.py
yafowil/widget/chosen/widget.py
yafowil/widget/chosen/resources/widget.css
yafowil/widget/chosen/resources/widget.js
yafowil/widget/chosen/resources/chosen/chosen-bootstrap.css
yafowil/widget/chosen/resources/chosen/chosen-sprite.png
yafowil/widget/chosen/resources/chosen/chosen-sprite@2x.png
yafowil/widget/chosen/resources/chosen/chosen.css
yafowil/widget/chosen/resources/chosen/chosen.jquery.js
yafowil/widget/chosen/resources/chosen/chosen.jquery.min.js
yafowil/widget/chosen/resources/chosen/chosen.min.css
yafowil/widget/chosen/resources/chosen/chosen.proto.js
yafowil/widget/chosen/resources/chosen/chosen.proto.min.js
yafowil_widget_chosen-1.4.dist-info/licenses/LICENSE.rst
yafowil_widget_chosen-1.4.dist-info/METADATA
yafowil_widget_chosen-1.4.dist-info/WHEEL
yafowil_widget_chosen-1.4.dist-info/entry_points.txt
yafowil_widget_chosen-1.4.dist-info/namespace_packages.txt
yafowil_widget_chosen-1.4.dist-info/top_level.txt
yafowil_widget_chosen-1.4.dist-info/RECORD
